
  [
    {
      "id": 5,
      "signatura": "BAN-001-27.jpg",
      "naziv": "Alibaba",
      "naziv_eng": "ono",
      "opis": "Galia est omnis divisa",
      "opis_eng": "ne",
      "lokacija": "Hrvatski Čuntić",
      "datum_sni": null,
      "kategorija": null,
      "autor": "Davor Konjikušić",
      "copyright": "CROATIAN LANDSCAPE",
      "copyright_holder": "-",
      "tagovi": "Å¡uma",
      "doi": null,
      "geom": "0101000020E6100000FFA10D7E6A493040E92B538D4EAE4640",
      "url_image": null,
      "url_thumb": null
    },
    {
      "id": 6,
      "signatura": "BAN-001-22.jpg",
      "naziv": "alo`",
      "naziv_eng": "medo",
      "opis": "in partes tres",
      "opis_eng": "zeko",
      "lokacija": "Hrvatski Čuntić",
      "datum_sni": null,
      "kategorija": null,
      "autor": "Davor Konjikušić",
      "copyright": "CROATIAN LANDSCAPE",
      "copyright_holder": "-",
      "tagovi": "samostan",
      "doi": null,
      "geom": "0101000020E610000006CB7A2E2B49304049630C5F6DAE4640",
      "url_image": null,
      "url_thumb": null
    },
    {
      "id": 7,
      "signatura": "BAN-001-34.jpg",
      "naziv": "ora",
      "naziv_eng": "nica",
      "opis": "quarum unam incolunt Belgai",
      "opis_eng": "zlica",
      "lokacija": "",
      "datum_sni": null,
      "kategorija": null,
      "autor": "Davor Konjikušić",
      "copyright": "CROATIAN LANDSCAPE",
      "copyright_holder": "-",
      "tagovi": "oranica",
      "doi": null,
      "geom": "0101000020E610000000000000000031400000000000804640",
      "url_image": null,
      "url_thumb": null
    },
    {
      "id": 8,
      "signatura": "BAN-001-47.jpg",
      "naziv": "Petrinja",
      "naziv_eng": "Petrinja",
      "opis": "hr",
      "opis_eng": "cro",
      "lokacija": "Hrvatski Čuntić",
      "datum_sni": null,
      "kategorija": null,
      "autor": "Davor Konjikušić",
      "copyright": "CROATIAN LANDSCAPE",
      "copyright_holder": "-",
      "tagovi": "oranica",
      "doi": null,
      "geom": "0101000020E610000009CDA60AE3483040E1D3A71601AF4640",
      "url_image": null,
      "url_thumb": null
    },
    {
      "id": 9,
      "signatura": "BAN-001-53.jpg",
      "naziv": "",
      "naziv_eng": "",
      "opis": "",
      "opis_eng": "",
      "lokacija": "Hrvatski Čuntić",
      "datum_sni": null,
      "kategorija": null,
      "autor": "Davor Konjikušić",
      "copyright": "CROATIAN LANDSCAPE",
      "copyright_holder": "-",
      "tagovi": "izvor",
      "doi": null,
      "geom": "0101000020E6100000538A5166ED483040F8881C4BEDAE4640",
      "url_image": null,
      "url_thumb": null
    },
    {
      "id": 10,
      "signatura": "BAN-001-53.jpg",
      "naziv": "",
      "naziv_eng": "",
      "opis": "",
      "opis_eng": "",
      "lokacija": "Hrvatski Čuntić",
      "datum_sni": null,
      "kategorija": null,
      "autor": "Davor Konjikušić",
      "copyright": "CROATIAN LANDSCAPE",
      "copyright_holder": "-",
      "tagovi": "izvor",
      "doi": null,
      "geom": "0101000020E6100000538A5166ED483040F8881C4BEDAE4640",
      "url_image": null,
      "url_thumb": null
    },
    {
      "id": 12,
      "signatura": "BAN-001-30.jpg",
      "naziv": "",
      "naziv_eng": "",
      "opis": "",
      "opis_eng": "",
      "lokacija": "Hrvatski Čuntić",
      "datum_sni": null,
      "kategorija": "infrastruktura",
      "autor": "Davor Konjikušić",
      "copyright": "CROATIAN LANDSCAPE",
      "copyright_holder": "-",
      "tagovi": "ploča, samostan",
      "doi": null,
      "geom": "0101000020E610000069C3FB5575493040FEA4E8EA4BAE4640",
      "url_image": null,
      "url_thumb": null
    },
    {
      "id": 13,
      "signatura": "BAN-001-2.jpg",
      "naziv": "",
      "naziv_eng": "",
      "opis": "",
      "opis_eng": "",
      "lokacija": "",
      "datum_sni": null,
      "kategorija": "ekologija",
      "autor": "Davor Konjikušić",
      "copyright": "CROATIAN LANDSCAPE",
      "copyright_holder": "-",
      "tagovi": "izvor",
      "doi": null,
      "geom": "0101000020E6100000A5E9FD90C84830400EAD30A9D7AD4640",
      "url_image": null,
      "url_thumb": null
    },
    {
      "id": 14,
      "signatura": "POS-001-99.jpg",
      "naziv": "",
      "naziv_eng": "",
      "opis": "",
      "opis_eng": "",
      "lokacija": "Drenov Bok",
      "datum_sni": null,
      "kategorija": "tradicijska_gradnja",
      "autor": "Davor Konjikušić",
      "copyright": "CROATIAN LANDSCAPE",
      "copyright_holder": "-",
      "tagovi": "dvorište,ograda",
      "doi": null,
      "geom": "0101000020E6100000CFC503EE1DD33040804FFCB21FA24640",
      "url_image": null,
      "url_thumb": null
    }
  ]